chordy/__init__.py
chordy/__main__.py
chordy/chord.py
chordy/segments.py
chordy/song.py
chordy-0.6.0.dist-info/METADATA
chordy-0.6.0.dist-info/WHEEL
chordy-0.6.0.dist-info/RECORD
